ovos_skill_confucius_quotes/LICENSE
ovos_skill_confucius_quotes/MANIFEST.in
ovos_skill_confucius_quotes/README.md
ovos_skill_confucius_quotes/__init__.py
ovos_skill_confucius_quotes/requirements.txt
ovos_skill_confucius_quotes/version.py
ovos_skill_confucius_quotes/gui/all/confucius.jpg
ovos_skill_confucius_quotes/gui/all/logo.jpeg
ovos_skill_confucius_quotes/locale/ca-es/birth.voc
ovos_skill_confucius_quotes/locale/ca-es/confucius.voc
ovos_skill_confucius_quotes/locale/ca-es/death.voc
ovos_skill_confucius_quotes/locale/ca-es/live.voc
ovos_skill_confucius_quotes/locale/ca-es/quote.voc
ovos_skill_confucius_quotes/locale/ca-es/skill.json
ovos_skill_confucius_quotes/locale/ca-es/when.voc
ovos_skill_confucius_quotes/locale/ca-es/who.intent
ovos_skill_confucius_quotes/locale/da/birth.dialog
ovos_skill_confucius_quotes/locale/da/birth.voc
ovos_skill_confucius_quotes/locale/da/confucius.dialog
ovos_skill_confucius_quotes/locale/da/confucius.voc
ovos_skill_confucius_quotes/locale/da/death.dialog
ovos_skill_confucius_quotes/locale/da/death.voc
ovos_skill_confucius_quotes/locale/da/live.dialog
ovos_skill_confucius_quotes/locale/da/live.voc
ovos_skill_confucius_quotes/locale/da/quote.dialog
ovos_skill_confucius_quotes/locale/da/quote.voc
ovos_skill_confucius_quotes/locale/da/skill.json
ovos_skill_confucius_quotes/locale/da/when.voc
ovos_skill_confucius_quotes/locale/da/who.intent
ovos_skill_confucius_quotes/locale/de-de/birth.dialog
ovos_skill_confucius_quotes/locale/de-de/birth.voc
ovos_skill_confucius_quotes/locale/de-de/confucius.dialog
ovos_skill_confucius_quotes/locale/de-de/confucius.voc
ovos_skill_confucius_quotes/locale/de-de/death.dialog
ovos_skill_confucius_quotes/locale/de-de/death.voc
ovos_skill_confucius_quotes/locale/de-de/live.dialog
ovos_skill_confucius_quotes/locale/de-de/live.voc
ovos_skill_confucius_quotes/locale/de-de/quote.dialog
ovos_skill_confucius_quotes/locale/de-de/quote.voc
ovos_skill_confucius_quotes/locale/de-de/skill.json
ovos_skill_confucius_quotes/ovos_skill_confucius_quotes.egg-info/PKG-INFO
ovos_skill_confucius_quotes/ovos_skill_confucius_quotes.egg-info/SOURCES.txt
ovos_skill_confucius_quotes/ovos_skill_confucius_quotes.egg-info/dependency_links.txt
ovos_skill_confucius_quotes/ovos_skill_confucius_quotes.egg-info/entry_points.txt
ovos_skill_confucius_quotes/ovos_skill_confucius_quotes.egg-info/requires.txt
ovos_skill_confucius_quotes/ovos_skill_confucius_quotes.egg-info/top_level.txt
ovos_skill_confucius_quotes-0.1.13.dist-info/LICENSE
ovos_skill_confucius_quotes-0.1.13.dist-info/METADATA
ovos_skill_confucius_quotes-0.1.13.dist-info/WHEEL
ovos_skill_confucius_quotes-0.1.13.dist-info/entry_points.txt
ovos_skill_confucius_quotes-0.1.13.dist-info/top_level.txt
ovos_skill_confucius_quotes-0.1.13.dist-info/RECORD
