Metadata-Version: 2.1
Name: ovos-skill-confucius-quotes
Version: 0.1.13
Summary: basic info and quotes from confucius
Home-page: https://github.com/OpenVoiceOS/ovos-skill-confucius-quotes
Author: OpenVoiceOS
Author-email: jarbasai@mailfence.com
License: Apache2.0
Keywords: ovos skill plugin
License-File: LICENSE
Requires-Dist: ovos-workshop<8.0.0,>=0.0.15
Requires-Dist: ovos-bus-client>=1.0.1
